oarepo_taxonomies/__init__.py
oarepo_taxonomies/cli.py
oarepo_taxonomies/config.py
oarepo_taxonomies/exceptions.py
oarepo_taxonomies/ext.py
oarepo_taxonomies/facets.py
oarepo_taxonomies/mappings.py
oarepo_taxonomies/marshmallow.py
oarepo_taxonomies/serializers.py
oarepo_taxonomies/signals.py
oarepo_taxonomies/tasks.py
oarepo_taxonomies/unflatten.py
oarepo_taxonomies/utils.py
oarepo_taxonomies/version.py
oarepo_taxonomies/datamodels/__init__.py
oarepo_taxonomies/datamodels/taxonomy-v2.0.0.json5
oarepo_taxonomies/import_export/__init__.py
oarepo_taxonomies/import_export/export_excel.py
oarepo_taxonomies/import_export/import_excel.py
oarepo_taxonomies/jsonschemas/__init__.py
oarepo_taxonomies/jsonschemas/taxonomy-v2.0.0.json
tests/__init__.py
tests/conftest.py
tests/helpers.py
tests/test_cli.py
tests/test_export_excel.py
tests/test_ext.py
tests/test_flask_taxonomies_api.py
tests/test_http_api.py
tests/test_import_excel.py
tests/test_jsonschemas.py
tests/test_mappings.py
tests/test_marshmallow.py
tests/test_permissions.py
tests/test_signals.py
tests/test_unflatten.py
tests/test_utils.py
oarepo_taxonomies-3.2.2.dist-info/LICENSE
oarepo_taxonomies-3.2.2.dist-info/METADATA
oarepo_taxonomies-3.2.2.dist-info/WHEEL
oarepo_taxonomies-3.2.2.dist-info/entry_points.txt
oarepo_taxonomies-3.2.2.dist-info/top_level.txt
oarepo_taxonomies-3.2.2.dist-info/RECORD
