Metadata-Version: 2.1
Name: oarepo-taxonomies
Version: 3.2.2
Summary: Wrapper that connect flask-taxonomies with Invenio
Home-page: https://github.com/oarepo/oarepo-taxonomies
Author: Daniel Kopecký
Author-email: Daniel.Kopecky@techlib.cz
License: MIT
Keywords: oarepo taxonomies
Platform: any
License-File: LICENSE
Requires-Dist: flask-taxonomies (>=7.0.0a17)
Requires-Dist: flatten-json (!=0.1.8,<1.0.0,>=0.1.7)
Requires-Dist: openpyxl (<4.0.0,>=3.0.4)
Requires-Dist: oarepo-mapping-includes (<2.0.0,>=1.2.0)
Requires-Dist: oarepo-references[validate] (<2.0.0,>=1.8.3)
Requires-Dist: deepmerge (>=0.1.0)
Requires-Dist: boltons (>=20.0.0)
Provides-Extra: tests
Requires-Dist: pytest ; extra == 'tests'
Requires-Dist: pytest-cov ; extra == 'tests'
Requires-Dist: oarepo (==3.3.26) ; extra == 'tests'
